tradeboy/__init__.py
tradeboy/tools.py
tradeboy/engines/__init__.py
tradeboy/engines/future.py
tradeboy/helpers/__init__.py
tradeboy/helpers/calc.py
tradeboy/helpers/exceptions.py
tradeboy/helpers/utility.py
tradeboy/tests/__init__.py
tradeboy/tests/tools_test.py
tradeboy-1.9.3.dist-info/LICENSE
tradeboy-1.9.3.dist-info/WHEEL
tradeboy-1.9.3.dist-info/METADATA
tradeboy-1.9.3.dist-info/RECORD
