Metadata-Version: 2.1
Name: tradeboy
Version: 1.9.3
Summary: Automated Crypto Trader
Author-email: Marques Traylor <traylorboy@proton.me>
Classifier: License :: OSI Approved :: MIT License
Requires-Dist: candleboy
Requires-Dist: phemexboy
Requires-Dist: python-dotenv
Requires-Dist: discordwebhook
Project-URL: Home, https://github.com/TraylorBoy/TradeBoy
